{
  "pokemon": [
    {
      "Number": 1,
      "Name": "Bulbasaur",
      "Card": "images\\PokemonCards-186.png",
      "Quantity": 1,
      "Set": "151 JP",
      "Code": "sv3pt5-1",
      "Language": "JP",
      "Special": null
    },
    {
      "Number": 2,
      "Name": "Ivysaur",
      "Card": "images\\PokemonCards-115.png",
      "Quantity": 1,
      "Set": "Secret Wonders",
      "Code": "dp3-51",
      "Language": "EN",
      "Special": null
    },
    {
      "Number": 4,
      "Name": "Charmander",
      "Card": "images\\PokemonCards-178.png",
      "Quantity": 1,
      "Set": "Dragon Majesty",
      "Code": "sm75-1",
      "Language": "EN",
      "Special": null
    },
    {
      "Number": 5,
      "Name": "Charmeleon",
      "Card": "images\\PokemonCards-6.png",
      "Quantity": 1,
      "Set": "Paldean Fates",
      "Code": "sv4pt5-8",
      "Language": "EN",
      "Special": null
    },
    {
      "Number": 5,
      "Name": "Charmeleon",
      "Card": "images\\PokemonCards-146.png",
      "Quantity": 1,
      "Set": "Secret Wonders",
      "Code": "dp3-46",
      "Language": "EN",
      "Special": null
    },
    {
      "Number": 5,
      "Name": "Charmeleon",
      "Card": "images\\PokemonCards-147.png",
      "Quantity": 1,
      "Set": "Crystal Guardians",
      "Code": "ex14-30",
      "Language": "EN",
      "Special": {
        "delta": true
      }
    },
    {
      "Number": 6,
      "Name": "Charizard",
      "Card": "images\\PokemonCards-49.png",
      "Quantity": 1,
      "Set": "Crystal Guardians",
      "Code": "ex14-4",
      "Language": "EN",
      "Special": {
        "delta": true
      }
    },
    {
      "Number": 7,
      "Name": "Squirtle",
      "Card": "images\\PokemonCards-30.png",
      "Quantity": 4,
      "Set": "Base Set 2",
      "Code": "base4-93",
      "Language": "EN",
      "Special": null
    },
    {
      "Number": 8,
      "Name": "Wartortle",
      "Card": "images\\PokemonCards-31.png",
      "Quantity": 1,
      "Set": "Crystal Guardians",
      "Code": "ex14-42",
      "Language": "EN",
      "Special": null
    },
    {
      "Number": 8,
      "Name": "Wartortle",
      "Card": "images\\PokemonCards-124.png",
      "Quantity": 1,
      "Set": "Base Set 2",
      "Code": "base4-63",
      "Language": "EN",
      "Special": null
    },
    {
      "Number": 9,
      "Name": "Blastoise",
      "Card": "images\\PokemonCards-32.png",
      "Quantity": 1,
      "Set": "FireRed & LeafGreen",
      "Code": "ex6-104",
      "Language": "EN",
      "Special": {
        "ex": true
      }
    },
    {
      "Number": 11,
      "Name": "Metapod",
      "Card": "images\\PokemonCards-187.png",
      "Quantity": 1,
      "Set": "151 JP",
      "Code": "sv3pt5-11",
      "Language": "JP",
      "Special": null
    },
    {
      "Number": 15,
      "Name": "Beedrill",
      "Card": "images\\PokemonCards-183.png",
      "Quantity": 1,
      "Set": "Unleashed",
      "Code": "hgss2-12",
      "Language": "EN",
      "Special": null
    },
    {
      "Number": 25,
      "Name": "Pikachu",
      "Card": "images\\PokemonCards-184.png",
      "Quantity": 1,
      "Set": "XY",
      "Code": "xy1-42",
      "Language": "EN",
      "Special": null
    },
    {
      "Number": 26,
      "Name": "Raichu",
      "Card": "images\\PokemonCards-35.png",
      "Quantity": 1,
      "Set": "Power Keepers",
      "Code": "ex16-12",
      "Language": "EN",
      "Special": null
    },
    {
      "Number": 29,
      "Name": "Nidoran♀",
      "Card": "images\\PokemonCards-122.png",
      "Quantity": 1,
      "Set": "Dragon Frontiers",
      "Code": "ex15-56",
      "Language": "EN",
      "Special": {
        "delta": true
      }
    },
    {
      "Number": 32,
      "Name": "Nidoran♂",
      "Card": "images\\PokemonCards-121.png",
      "Quantity": 1,
      "Set": "Dragon Frontiers",
      "Code": "ex15-57",
      "Language": "EN",
      "Special": {
        "delta": true
      }
    },
    {
      "Number": 35,
      "Name": "Clefairy",
      "Card": "images\\PokemonCards-102.png",
      "Quantity": 1,
      "Set": "Unseen Forces",
      "Code": "ex10-53",
      "Language": "EN",
      "Special": null
    },
    {
      "Number": 36,
      "Name": "Clefable",
      "Card": "images\\PokemonCards-103.png",
      "Quantity": 1,
      "Set": "Jungle",
      "Code": "base2-1",
      "Language": "EN",
      "Special": null
    },
    {
      "Number": 38,
      "Name": "Ninetales",
      "Card": "images\\PokemonCards-24.png",
      "Quantity": 1,
      "Set": "Mysterious Treasures",
      "Code": "dp2-32",
      "Language": "EN",
      "Special": null
    },
    {
      "Number": 39,
      "Name": "Jigglypuff",
      "Card": "images\\PokemonCards-101.png",
      "Quantity": 3,
      "Set": "Base Set 2",
      "Code": "base4-77",
      "Language": "EN",
      "Special": null
    },
    {
      "Number": 40,
      "Name": "Wigglytuff",
      "Card": "images\\PokemonCards-43.png",
      "Quantity": 1,
      "Set": "Jungle",
      "Code": "base2-32",
      "Language": "EN",
      "Special": null
    },
    {
      "Number": 46,
      "Name": "Paras",
      "Card": "images\\PokemonCards-34.png",
      "Quantity": 1,
      "Set": "Mysterious Treasures",
      "Code": "dp2-92",
      "Language": "EN",
      "Special": null
    },
    {
      "Number": 51,
      "Name": "Dugtrio",
      "Card": "images\\PokemonCards-33.png",
      "Quantity": 1,
      "Set": "Crystal Guardians",
      "Code": "ex14-5",
      "Language": "EN",
      "Special": null
    },
    {
      "Number": 54,
      "Name": "Psyduck",
      "Card": "images\\PokemonCards-106.png",
      "Quantity": 1,
      "Set": "Gym Challenge",
      "Code": "gym2-99",
      "Language": "EN",
      "Special": {
        "Trainer Pokemon": "Sabrina's Psyduck"
      }
    },
    {
      "Number": 59,
      "Name": "Arcanine",
      "Card": "images\\PokemonCards-26.png",
      "Quantity": 1,
      "Set": "Secret Wonders",
      "Code": "dp3-22",
      "Language": "EN",
      "Special": null
    },
    {
      "Number": 60,
      "Name": "Poliwag",
      "Card": "images\\PokemonCards-9.png",
      "Quantity": 1,
      "Set": "Unseen Forces",
      "Code": "uf-67",
      "Language": "EN",
      "Special": null
    },
    {
      "Number": 63,
      "Name": "Abra",
      "Card": "images\\PokemonCards-10.png",
      "Quantity": 3,
      "Set": "Base Set 2",
      "Code": "base4-65",
      "Language": "EN",
      "Special": null
    },
    {
      "Number": 64,
      "Name": "Kadabra",
      "Card": "images\\PokemonCards-108.png",
      "Quantity": 1,
      "Set": "Base Set 2",
      "Code": "base4-46",
      "Language": "EN",
      "Special": null
    },
    {
      "Number": 66,
      "Name": "Machop",
      "Card": "images\\PokemonCards-109.png",
      "Quantity": 1,
      "Set": "Diamond & Pearl",
      "Code": "dp1-86",
      "Language": "EN",
      "Special": null
    },
    {
      "Number": 66,
      "Name": "Machop",
      "Card": "images\\PokemonCards-129.png",
      "Quantity": 1,
      "Set": "Power Keepers",
      "Code": "ex16-53",
      "Language": "EN",
      "Special": null
    },
    {
      "Number": 68,
      "Name": "Machamp",
      "Card": "images\\PokemonCards-110.png",
      "Quantity": 1,
      "Set": "Diamond & Pearl",
      "Code": "dp1-31",
      "Language": "EN",
      "Special": null
    },
    {
      "Number": 75,
      "Name": "Graveler",
      "Card": "images\\PokemonCards-130.png",
      "Quantity": 1,
      "Set": "Mysterious Treasures",
      "Code": "dp2-51",
      "Language": "EN",
      "Special": null
    },
    {
      "Number": 78,
      "Name": "Rapidash",
      "Card": "images\\PokemonCards-141.png",
      "Quantity": 1,
      "Set": "Diamond & Pearl",
      "Code": "dp1-59",
      "Language": "EN",
      "Special": null
    },
    {
      "Number": 80,
      "Name": "Slowbro",
      "Card": "images\\PokemonCards-41.png",
      "Quantity": 1,
      "Set": "Great Encounters",
      "Code": "dp4-54",
      "Language": "EN",
      "Special": null
    },
    {
      "Number": 81,
      "Name": "Magnemite",
      "Card": "images\\PokemonCards-15.png",
      "Quantity": 1,
      "Set": "Delta Species",
      "Code": "ex11-70",
      "Language": "EN",
      "Special": {
        "delta": true,
        "Trainer Pokemon": "Holon's Magnemite"
      }
    },
    {
      "Number": 81,
      "Name": "Magnemite",
      "Card": "images\\PokemonCards-104.png",
      "Quantity": 1,
      "Set": "Power Keepers",
      "Code": "ex16-54",
      "Language": "EN",
      "Special": null
    },
    {
      "Number": 86,
      "Name": "Seel",
      "Card": "images\\PokemonCards-99.png",
      "Quantity": 1,
      "Set": "Base Set 2",
      "Code": "base4-61",
      "Language": "EN",
      "Special": null
    },
    {
      "Number": 95,
      "Name": "Onix",
      "Card": "images\\PokemonCards-138.png",
      "Quantity": 1,
      "Set": "Diamond & Pearl",
      "Code": "dp1-92",
      "Language": "EN",
      "Special": null
    },
    {
      "Number": 96,
      "Name": "Drowzee",
      "Card": "images\\PokemonCards-90.png",
      "Quantity": 2,
      "Set": "Base Set 2",
      "Code": "base4-73",
      "Language": "EN",
      "Special": null
    },
    {
      "Number": 98,
      "Name": "Krabby",
      "Card": "images\\PokemonCards-96.png",
      "Quantity": 1,
      "Set": "Crystal Guardians",
      "Code": "ex14-54",
      "Language": "EN",
      "Special": null
    },
    {
      "Number": 109,
      "Name": "Koffing",
      "Card": "images\\PokemonCards-94.png",
      "Quantity": 1,
      "Set": "Team Rocket",
      "Code": "base5-58",
      "Language": "EN",
      "Special": null
    },
    {
      "Number": 115,
      "Name": "Kangaskhan",
      "Card": "images\\PokemonCards-119.png",
      "Quantity": 1,
      "Set": "Jungle",
      "Code": "base2-21",
      "Language": "EN",
      "Special": null
    },
    {
      "Number": 118,
      "Name": "Goldeen",
      "Card": "images\\PokemonCards-145.png",
      "Quantity": 1,
      "Set": "Diamond & Pearl",
      "Code": "dp1-84",
      "Language": "EN",
      "Special": null
    },
    {
      "Number": 120,
      "Name": "Staryu",
      "Card": "images\\PokemonCards-88.png",
      "Quantity": 3,
      "Set": "Base Set 2",
      "Code": "base4-95",
      "Language": "EN",
      "Special": null
    },
    {
      "Number": 121,
      "Name": "Starmie",
      "Card": "images\\PokemonCards-85.png",
      "Quantity": 1,
      "Set": "Base Set 2",
      "Code": "base4-94",
      "Language": "EN",
      "Special": null
    },
    {
      "Number": 123,
      "Name": "Scyther",
      "Card": "images\\PokemonCards-18.png",
      "Quantity": 1,
      "Set": "Majestic Dawn",
      "Code": "dp5-46",
      "Language": "EN",
      "Special": null
    },
    {
      "Number": 124,
      "Name": "Jynx",
      "Card": "images\\PokemonCards-97.png",
      "Quantity": 2,
      "Set": "Base Set 2",
      "Code": "base4-45",
      "Language": "EN",
      "Special": null
    },
    {
      "Number": 125,
      "Name": "Electabuzz",
      "Card": "images\\PokemonCards-20.png",
      "Quantity": 1,
      "Set": "Diamond & Pearl",
      "Code": "dp1-81",
      "Language": "EN",
      "Special": null
    },
    {
      "Number": 125,
      "Name": "Electabuzz",
      "Card": "images\\PokemonCards-86.png",
      "Quantity": 1,
      "Set": "Dragon Frontiers",
      "Code": "ex15-29",
      "Language": "EN",
      "Special": {
        "delta": true
      }
    },
    {
      "Number": 130,
      "Name": "Gyarados",
      "Card": "images\\PokemonCards-42.png",
      "Quantity": 1,
      "Set": "Holon Phantoms",
      "Code": "ex13-8",
      "Language": "EN",
      "Special": {
        "delta": true
      }
    },
    {
      "Number": 131,
      "Name": "Lapras",
      "Card": "images\\PokemonCards-79.png",
      "Quantity": 1,
      "Set": "Ruby & Sapphire",
      "Code": "ex1-99",
      "Language": "EN",
      "Special": {
        "ex": true
      }
    },
    {
      "Number": 134,
      "Name": "Vaporeon",
      "Card": "images\\PokemonCards-65.png",
      "Quantity": 1,
      "Set": "POP Series 3",
      "Code": "pop3-6",
      "Language": "EN",
      "Special": null
    },
    {
      "Number": 135,
      "Name": "Jolteon",
      "Card": "images\\PokemonCards-56.png",
      "Quantity": 1,
      "Set": "POP Series 3",
      "Code": "pop3-3",
      "Language": "EN",
      "Special": null
    },
    {
      "Number": 135,
      "Name": "Jolteon",
      "Card": "images\\PokemonCards-57.png",
      "Quantity": 2,
      "Set": "Delta Species",
      "Code": "ex11-109",
      "Language": "EN",
      "Special": {
        "ex": true
      }
    },
    {
      "Number": 140,
      "Name": "Kabuto",
      "Card": "images\\PokemonCards-87.png",
      "Quantity": 1,
      "Set": "Majestic Dawn",
      "Code": "dp5-67",
      "Language": "EN",
      "Special": null
    },
    {
      "Number": 141,
      "Name": "Kabutops",
      "Card": "images\\PokemonCards-54.png",
      "Quantity": 1,
      "Set": "Holon Phantoms",
      "Code": "ex13-9",
      "Language": "EN",
      "Special": {
        "delta": true
      }
    },
    {
      "Number": 147,
      "Name": "Dratini",
      "Card": "images\\PokemonCards-134.png",
      "Quantity": 1,
      "Set": "Dragon Frontiers",
      "Code": "ex15-46",
      "Language": "EN",
      "Special": {
        "delta": true
      }
    },
    {
      "Number": 148,
      "Name": "Dragonair",
      "Card": "images\\PokemonCards-171.png",
      "Quantity": 1,
      "Set": "151 JP",
      "Code": "sv3pt5-181",
      "Language": "JP",
      "Special": null
    },
    {
      "Number": 149,
      "Name": "Dragonite",
      "Card": "images\\PokemonCards-59.png",
      "Quantity": 1,
      "Set": "Legends Awakened",
      "Code": "dp6-2",
      "Language": "EN",
      "Special": null
    },
    {
      "Number": 155,
      "Name": "Cyndaquil",
      "Card": "images\\PokemonCards-151.png",
      "Quantity": 1,
      "Set": "Dragon Frontiers",
      "Code": "ex15-45",
      "Language": "EN",
      "Special": {
        "delta": true
      }
    },
    {
      "Number": 157,
      "Name": "Typhlosion",
      "Card": "images\\PokemonCards-45.png",
      "Quantity": 1,
      "Set": "Unseen Forces",
      "Code": "ex10-17",
      "Language": "EN",
      "Special": null
    },
    {
      "Number": 170,
      "Name": "Chinchou",
      "Card": "images\\PokemonCards-25.png",
      "Quantity": 1,
      "Set": "Power Keepers",
      "Code": "ex16-49",
      "Language": "EN",
      "Special": null
    },
    {
      "Number": 172,
      "Name": "Pichu",
      "Card": "images\\PokemonCards-107.png",
      "Quantity": 1,
      "Set": "Power Keepers",
      "Code": "ex16-21",
      "Language": "EN",
      "Special": null
    },
    {
      "Number": 178,
      "Name": "Xatu",
      "Card": "images\\PokemonCards-98.png",
      "Quantity": 1,
      "Set": "Dragon Frontiers",
      "Code": "ex15-25",
      "Language": "EN",
      "Special": {
        "delta": true
      }
    },
    {
      "Number": 181,
      "Name": "Ampharos",
      "Card": "images\\PokemonCards-52.png",
      "Quantity": 1,
      "Set": "Dragon Frontiers",
      "Code": "ex15-1",
      "Language": "EN",
      "Special": {
        "delta": true
      }
    },
    {
      "Number": 183,
      "Name": "Marill",
      "Card": "images\\PokemonCards-128.png",
      "Quantity": 1,
      "Set": "Diamond & Pearl",
      "Code": "dp1-88",
      "Language": "EN",
      "Special": null
    },
    {
      "Number": 185,
      "Name": "Sudowoodo",
      "Card": "images\\PokemonCards-8.png",
      "Quantity": 1,
      "Set": "Mysterious Treasures",
      "Code": "dp2-35",
      "Language": "EN",
      "Special": null
    },
    {
      "Number": 192,
      "Name": "Sunflora",
      "Card": "images\\PokemonCards-123.png",
      "Quantity": 1,
      "Set": "Secret Wonders",
      "Code": "dp3-38",
      "Language": "EN",
      "Special": null
    },
    {
      "Number": 194,
      "Name": "Wooper",
      "Card": "images\\PokemonCards-127.png",
      "Quantity": 1,
      "Set": "Team Rocket Returns",
      "Code": "ex7-81",
      "Language": "EN",
      "Special": null
    },
    {
      "Number": 197,
      "Name": "Umbreon",
      "Card": "images\\PokemonCards-61.png",
      "Quantity": 1,
      "Set": "Majestic Dawn",
      "Code": "dp5-32",
      "Language": "EN",
      "Special": null
    },
    {
      "Number": 202,
      "Name": "Wobbuffet",
      "Card": "images\\PokemonCards-92.png",
      "Quantity": 1,
      "Set": "Holon Phantoms",
      "Code": "ex13-56",
      "Language": "EN",
      "Special": null
    },
    {
      "Number": 202,
      "Name": "Wobbuffet",
      "Card": "images\\PokemonCards-137.png",
      "Quantity": 1,
      "Set": "Power Keepers",
      "Code": "ex16-24",
      "Language": "EN",
      "Special": null
    },
    {
      "Number": 204,
      "Name": "Pineco",
      "Card": "images\\PokemonCards-2.png",
      "Quantity": 1,
      "Set": "Paldean Fates",
      "Code": "sv4pt5-1",
      "Language": "EN",
      "Special": null
    },
    {
      "Number": 205,
      "Name": "Forretress",
      "Card": "images\\PokemonCards-39.png",
      "Quantity": 1,
      "Set": "Legends Awakened",
      "Code": "dp6-28",
      "Language": "EN",
      "Special": null
    },
    {
      "Number": 209,
      "Name": "Snubbull",
      "Card": "images\\PokemonCards-100.png",
      "Quantity": 1,
      "Set": "Unseen Forces",
      "Code": "ex10-74",
      "Language": "EN",
      "Special": null
    },
    {
      "Number": 212,
      "Name": "Scizor",
      "Card": "images\\PokemonCards-81.png",
      "Quantity": 1,
      "Set": "Unseen Forces",
      "Code": "ex10-108",
      "Language": "EN",
      "Special": {
        "ex": true
      }
    },
    {
      "Number": 219,
      "Name": "Magcargo",
      "Card": "images\\PokemonCards-46.png",
      "Quantity": 1,
      "Set": "Great Encounters",
      "Code": "dp4-45",
      "Language": "EN",
      "Special": null
    },
    {
      "Number": 227,
      "Name": "Skarmory",
      "Card": "images\\PokemonCards-74.png",
      "Quantity": 1,
      "Set": "Power Keepers",
      "Code": "ex16-98",
      "Language": "EN",
      "Special": {
        "ex": true
      }
    },
    {
      "Number": 230,
      "Name": "Kingdra",
      "Card": "images\\PokemonCards-50.png",
      "Quantity": 1,
      "Set": "Holon Phantoms",
      "Code": "ex13-10",
      "Language": "EN",
      "Special": {
        "delta": true
      }
    },
    {
      "Number": 240,
      "Name": "Magby",
      "Card": "images\\PokemonCards-89.png",
      "Quantity": 1,
      "Set": "Mysterious Treasures",
      "Code": "dp2-88",
      "Language": "EN",
      "Special": null
    },
    {
      "Number": 243,
      "Name": "Raikou",
      "Card": "images\\PokemonCards-175.png",
      "Quantity": 1,
      "Set": "Shining Legends",
      "Code": "sm35-32",
      "Language": "EN",
      "Special": null
    },
    {
      "Number": 244,
      "Name": "Entei",
      "Card": "images\\PokemonCards-182.png",
      "Quantity": 1,
      "Set": "Paldean Fates",
      "Code": "sv4pt5-112",
      "Language": "EN",
      "Special": null
    },
    {
      "Number": 247,
      "Name": "Pupitar",
      "Card": "images\\PokemonCards-148.png",
      "Quantity": 1,
      "Set": "Dragon Frontiers",
      "Code": "ex15-59",
      "Language": "EN",
      "Special": {
        "delta": true
      }
    },
    {
      "Number": 248,
      "Name": "Tyranitar",
      "Card": "images\\PokemonCards-47.png",
      "Quantity": 1,
      "Set": "Delta Species",
      "Code": "ex11-16",
      "Language": "EN",
      "Special": {
        "delta": true
      }
    },
    {
      "Number": 248,
      "Name": "Tyranitar",
      "Card": "images\\PokemonCards-63.png",
      "Quantity": 1,
      "Set": "Mysterious Treasures",
      "Code": "dp2-17",
      "Language": "EN",
      "Special": null
    },
    {
      "Number": 248,
      "Name": "Tyranitar",
      "Card": "images\\PokemonCards-75.png",
      "Quantity": 1,
      "Set": "POP Series 1",
      "Code": "pop1-17",
      "Language": "EN",
      "Special": {
        "ex": true
      }
    },
    {
      "Number": 249,
      "Name": "Lugia",
      "Card": "images\\PokemonCards-174.png",
      "Quantity": 1,
      "Set": "Paradigm Trigger JP",
      "Code": "swsh12-138",
      "Language": "JP",
      "Special": {
        "V": true
      }
    },
    {
      "Number": 254,
      "Name": "Sceptile",
      "Card": "images\\PokemonCards-40.png",
      "Quantity": 1,
      "Set": "Ruby & Sapphire",
      "Code": "ex1-11",
      "Language": "EN",
      "Special": null
    },
    {
      "Number": 256,
      "Name": "Combusken",
      "Card": "images\\PokemonCards-84.png",
      "Quantity": 1,
      "Set": "Crystal Guardians",
      "Code": "ex14-31",
      "Language": "EN",
      "Special": null
    },
    {
      "Number": 256,
      "Name": "Combusken",
      "Card": "images\\PokemonCards-139.png",
      "Quantity": 1,
      "Set": "Power Keepers",
      "Code": "ex16-29",
      "Language": "EN",
      "Special": null
    },
    {
      "Number": 261,
      "Name": "Poochyena",
      "Card": "images\\PokemonCards-117.png",
      "Quantity": 1,
      "Set": "Power Keepers",
      "Code": "ex16-58",
      "Language": "EN",
      "Special": null
    },
    {
      "Number": 263,
      "Name": "Zigzagoon",
      "Card": "images\\PokemonCards-19.png",
      "Quantity": 1,
      "Set": "EX Trainer Kit Latios",
      "Code": "tk1b-7",
      "Language": "EN",
      "Special": null
    },
    {
      "Number": 267,
      "Name": "Beautifly",
      "Card": "images\\PokemonCards-16.png",
      "Quantity": 1,
      "Set": "Diamond & Pearl",
      "Code": "dp1-19",
      "Language": "EN",
      "Special": null
    },
    {
      "Number": 271,
      "Name": "Lombre",
      "Card": "images\\PokemonCards-38.png",
      "Quantity": 1,
      "Set": "Deoxys",
      "Code": "ex8-33",
      "Language": "EN",
      "Special": null
    },
    {
      "Number": 272,
      "Name": "Ludicolo",
      "Card": "images\\PokemonCards-116.png",
      "Quantity": 1,
      "Set": "Deoxys",
      "Code": "ex8-19",
      "Language": "EN",
      "Special": null
    },
    {
      "Number": 273,
      "Name": "Seedot",
      "Card": "images\\PokemonCards-95.png",
      "Quantity": 1,
      "Set": "Diamond & Pearl",
      "Code": "dp1-97",
      "Language": "EN",
      "Special": null
    },
    {
      "Number": 274,
      "Name": "Nuzleaf",
      "Card": "images\\PokemonCards-21.png",
      "Quantity": 1,
      "Set": "Power Keepers",
      "Code": "ex16-36",
      "Language": "EN",
      "Special": null
    },
    {
      "Number": 275,
      "Name": "Shiftry",
      "Card": "images\\PokemonCards-172.png",
      "Quantity": 1,
      "Set": "Cyber Judge JP",
      "Code": "sv5-163",
      "Language": "JP",
      "Special": null
    },
    {
      "Number": 280,
      "Name": "Ralts",
      "Card": "images\\PokemonCards-0.png",
      "Quantity": 1,
      "Set": "Paldean Fates",
      "Code": "sv4pt5-27",
      "Language": "EN",
      "Special": null
    },
    {
      "Number": 282,
      "Name": "Gardevoir",
      "Card": "images\\PokemonCards-7.png",
      "Quantity": 1,
      "Set": "Paldean Fates",
      "Code": "sv4pt5-217",
      "Language": "EN",
      "Special": {
        "ex": true
      }
    },
    {
      "Number": 282,
      "Name": "Gardevoir",
      "Card": "images\\PokemonCards-68.png",
      "Quantity": 1,
      "Set": "Sandstorm",
      "Code": "ex2-96",
      "Language": "EN",
      "Special": {
        "ex": true
      }
    },
    {
      "Number": 305,
      "Name": "Lairon",
      "Card": "images\\PokemonCards-17.png",
      "Quantity": 1,
      "Set": "Crystal Guardians",
      "Code": "ex14-36",
      "Language": "EN",
      "Special": null
    },
    {
      "Number": 306,
      "Name": "Aggron",
      "Card": "images\\PokemonCards-36.png",
      "Quantity": 1,
      "Set": "Crystal Guardians",
      "Code": "ex14-89",
      "Language": "EN",
      "Special": {
        "ex": true
      }
    },
    {
      "Number": 309,
      "Name": "Electrike",
      "Card": "images\\PokemonCards-113.png",
      "Quantity": 1,
      "Set": "Mysterious Treasures",
      "Code": "dp2-81",
      "Language": "EN",
      "Special": null
    },
    {
      "Number": 310,
      "Name": "Manectric",
      "Card": "images\\PokemonCards-112.png",
      "Quantity": 1,
      "Set": "Holon Phantoms",
      "Code": "ex13-46",
      "Language": "EN",
      "Special": null
    },
    {
      "Number": 319,
      "Name": "Sharpedo",
      "Card": "images\\PokemonCards-132.png",
      "Quantity": 1,
      "Set": "Ruby & Sapphire",
      "Code": "ex1-22",
      "Language": "EN",
      "Special": null
    },
    {
      "Number": 322,
      "Name": "Numel",
      "Card": "images\\PokemonCards-3.png",
      "Quantity": 1,
      "Set": "Paldean Fates",
      "Code": "sv4pt5-11",
      "Language": "EN",
      "Special": null
    },
    {
      "Number": 323,
      "Name": "Camerupt",
      "Card": "images\\PokemonCards-5.png",
      "Quantity": 1,
      "Set": "Paldean Fates",
      "Code": "sv4pt5-12",
      "Language": "EN",
      "Special": null
    },
    {
      "Number": 326,
      "Name": "Grumpig",
      "Card": "images\\PokemonCards-83.png",
      "Quantity": 1,
      "Set": "Crystal Guardians",
      "Code": "ex14-20",
      "Language": "EN",
      "Special": null
    },
    {
      "Number": 326,
      "Name": "Grumpig",
      "Card": "images\\PokemonCards-111.png",
      "Quantity": 1,
      "Set": "Deoxys",
      "Code": "ex8-32",
      "Language": "EN",
      "Special": null
    },
    {
      "Number": 328,
      "Name": "Trapinch",
      "Card": "images\\PokemonCards-152.png",
      "Quantity": 1,
      "Set": "Power Keepers",
      "Code": "ex16-68",
      "Language": "EN",
      "Special": null
    },
    {
      "Number": 330,
      "Name": "Flygon",
      "Card": "images\\PokemonCards-66.png",
      "Quantity": 1,
      "Set": "Dragon Frontiers",
      "Code": "ex15-92",
      "Language": "EN",
      "Special": {
        "ex": true,
        "delta": true
      }
    },
    {
      "Number": 331,
      "Name": "Cacnea",
      "Card": "images\\PokemonCards-22.png",
      "Quantity": 1,
      "Set": "Power Keepers",
      "Code": "ex16-46",
      "Language": "EN",
      "Special": null
    },
    {
      "Number": 333,
      "Name": "Swablu",
      "Card": "images\\PokemonCards-120.png",
      "Quantity": 1,
      "Set": "Power Keepers",
      "Code": "ex16-66",
      "Language": "EN",
      "Special": null
    },
    {
      "Number": 334,
      "Name": "Altaria",
      "Card": "images\\PokemonCards-37.png",
      "Quantity": 1,
      "Set": "Power Keepers",
      "Code": "ex16-2",
      "Language": "EN",
      "Special": null
    },
    {
      "Number": 334,
      "Name": "Altaria",
      "Card": "images\\PokemonCards-114.png",
      "Quantity": 1,
      "Set": "Great Encounters",
      "Code": "dp4-12",
      "Language": "EN",
      "Special": null
    },
    {
      "Number": 335,
      "Name": "Zangoose",
      "Card": "images\\PokemonCards-181.png",
      "Quantity": 1,
      "Set": "Team Up",
      "Code": "sm9-132",
      "Language": "EN",
      "Special": null
    },
    {
      "Number": 340,
      "Name": "Whiscash",
      "Card": "images\\PokemonCards-140.png",
      "Quantity": 1,
      "Set": "Holon Phantoms",
      "Code": "ex13-55",
      "Language": "EN",
      "Special": null
    },
    {
      "Number": 342,
      "Name": "Crawdaunt",
      "Card": "images\\PokemonCards-70.png",
      "Quantity": 1,
      "Set": "Deoxys",
      "Code": "ex8-6",
      "Language": "EN",
      "Special": null
    },
    {
      "Number": 345,
      "Name": "Lileep",
      "Card": "images\\PokemonCards-13.png",
      "Quantity": 1,
      "Set": "Holon Phantoms",
      "Code": "hp-68",
      "Language": "EN",
      "Special": {
        "delta": true
      }
    },
    {
      "Number": 348,
      "Name": "Armaldo",
      "Card": "images\\PokemonCards-78.png",
      "Quantity": 1,
      "Set": "POP Series 1",
      "Code": "pop1-16",
      "Language": "EN",
      "Special": {
        "ex": true
      }
    },
    {
      "Number": 348,
      "Name": "Armaldo",
      "Card": "images\\PokemonCards-126.png",
      "Quantity": 1,
      "Set": "Legends Awakened",
      "Code": "dp6-18",
      "Language": "EN",
      "Special": null
    },
    {
      "Number": 354,
      "Name": "Banette",
      "Card": "images\\PokemonCards-64.png",
      "Quantity": 1,
      "Set": "Legend Maker",
      "Code": "ex12-85",
      "Language": "EN",
      "Special": {
        "ex": true
      }
    },
    {
      "Number": 355,
      "Name": "Duskull",
      "Card": "images\\PokemonCards-12.png",
      "Quantity": 1,
      "Set": "Power Keepers",
      "Code": "ex16-50",
      "Language": "EN",
      "Special": null
    },
    {
      "Number": 356,
      "Name": "Dusclops",
      "Card": "images\\PokemonCards-105.png",
      "Quantity": 1,
      "Set": "Diamond & Pearl",
      "Code": "dp1-47",
      "Language": "EN",
      "Special": null
    },
    {
      "Number": 359,
      "Name": "Absol",
      "Card": "images\\PokemonCards-72.png",
      "Quantity": 1,
      "Set": "Power Keepers",
      "Code": "ex16-92",
      "Language": "EN",
      "Special": {
        "ex": true
      }
    },
    {
      "Number": 359,
      "Name": "Absol",
      "Card": "images\\PokemonCards-73.png",
      "Quantity": 1,
      "Set": "Holon Phantoms",
      "Code": "ex13-18",
      "Language": "EN",
      "Special": null
    },
    {
      "Number": 362,
      "Name": "Glalie",
      "Card": "images\\PokemonCards-23.png",
      "Quantity": 1,
      "Set": "Hidden Legends",
      "Code": "ex5-34",
      "Language": "EN",
      "Special": null
    },
    {
      "Number": 363,
      "Name": "Spheal",
      "Card": "images\\PokemonCards-149.png",
      "Quantity": 1,
      "Set": "Mysterious Treasures",
      "Code": "dp2-102",
      "Language": "EN",
      "Special": null
    },
    {
      "Number": 363,
      "Name": "Spheal",
      "Card": "images\\PokemonCards-150.png",
      "Quantity": 1,
      "Set": "Power Keepers",
      "Code": "ex16-65",
      "Language": "EN",
      "Special": null
    },
    {
      "Number": 364,
      "Name": "Sealeo",
      "Card": "images\\PokemonCards-91.png",
      "Quantity": 1,
      "Set": "Power Keepers",
      "Code": "ex16-37",
      "Language": "EN",
      "Special": null
    },
    {
      "Number": 365,
      "Name": "Walrein",
      "Card": "images\\PokemonCards-48.png",
      "Quantity": 1,
      "Set": "Team Magma vs Team Aqua",
      "Code": "ex4-6",
      "Language": "EN",
      "Special": {
        "Trainer Pokemon": "Team Aqua's Walrein"
      }
    },
    {
      "Number": 373,
      "Name": "Salamence",
      "Card": "images\\PokemonCards-60.png",
      "Quantity": 1,
      "Set": "Secret Wonders",
      "Code": "dp3-18",
      "Language": "EN",
      "Special": null
    },
    {
      "Number": 374,
      "Name": "Beldum",
      "Card": "images\\PokemonCards-118.png",
      "Quantity": 1,
      "Set": "Power Keepers",
      "Code": "ex16-45",
      "Language": "EN",
      "Special": null
    },
    {
      "Number": 376,
      "Name": "Metagross",
      "Card": "images\\PokemonCards-143.png",
      "Quantity": 1,
      "Set": "Power Keepers",
      "Code": "ex16-95",
      "Language": "EN",
      "Special": {
        "ex": true
      }
    },
    {
      "Number": 376,
      "Name": "Metagross",
      "Card": "images\\PokemonCards-144.png",
      "Quantity": 1,
      "Set": "POP Series 1",
      "Code": "pop1-2",
      "Language": "EN",
      "Special": null
    },
    {
      "Number": 380,
      "Name": "Latias",
      "Card": "images\\PokemonCards-80.png",
      "Quantity": 1,
      "Set": "Dragon",
      "Code": "ex3-93",
      "Language": "EN",
      "Special": {
        "ex": true
      }
    },
    {
      "Number": 384,
      "Name": "Rayquaza",
      "Card": "images\\PokemonCards-69.png",
      "Quantity": 1,
      "Set": "Dragon Frontiers",
      "Code": "ex15-97",
      "Language": "EN",
      "Special": {
        "ex": true,
        "delta": true
      }
    },
    {
      "Number": 385,
      "Name": "Jirachi",
      "Card": "images\\PokemonCards-71.png",
      "Quantity": 1,
      "Set": "Crystal Guardians",
      "Code": "ex14-94",
      "Language": "EN",
      "Special": {
        "ex": true
      }
    },
    {
      "Number": 386,
      "Name": "Deoxys",
      "Card": "images\\PokemonCards-180.png",
      "Quantity": 1,
      "Set": "Celestial Storm",
      "Code": "sm7-69",
      "Language": "EN",
      "Special": null
    },
    {
      "Number": 389,
      "Name": "Torterra",
      "Card": "images\\PokemonCards-76.png",
      "Quantity": 1,
      "Set": "DP Black Star Promos",
      "Code": "dpp-dp09",
      "Language": "EN",
      "Special": {
        "LV. X": true
      }
    },
    {
      "Number": 390,
      "Name": "Chimchar",
      "Card": "images\\PokemonCards-27.png",
      "Quantity": 1,
      "Set": "Diamond & Pearl",
      "Code": "dp1-76",
      "Language": "EN",
      "Special": null
    },
    {
      "Number": 390,
      "Name": "Chimchar",
      "Card": "images\\PokemonCards-62.png",
      "Quantity": 1,
      "Set": "Majestic Dawn",
      "Code": "dp5-56",
      "Language": "EN",
      "Special": null
    },
    {
      "Number": 391,
      "Name": "Monferno",
      "Card": "images\\PokemonCards-28.png",
      "Quantity": 1,
      "Set": "Diamond & Pearl",
      "Code": "dp1-56",
      "Language": "EN",
      "Special": null
    },
    {
      "Number": 392,
      "Name": "Infernape",
      "Card": "images\\PokemonCards-29.png",
      "Quantity": 1,
      "Set": "DP Black Star Promos",
      "Code": "dpp-dp10",
      "Language": "EN",
      "Special": {
        "LV. X": true
      }
    },
    {
      "Number": 395,
      "Name": "Empoleon",
      "Card": "images\\PokemonCards-58.png",
      "Quantity": 1,
      "Set": "Diamond & Pearl",
      "Code": "dp1-4",
      "Language": "EN",
      "Special": null
    },
    {
      "Number": 395,
      "Name": "Empoleon",
      "Card": "images\\PokemonCards-77.png",
      "Quantity": 1,
      "Set": "Diamond & Pearl",
      "Code": "dp1-120",
      "Language": "EN",
      "Special": {
        "LV. X": true
      }
    },
    {
      "Number": 402,
      "Name": "Kricketune",
      "Card": "images\\PokemonCards-136.png",
      "Quantity": 1,
      "Set": "Mysterious Treasures",
      "Code": "dp2-27",
      "Language": "EN",
      "Special": null
    },
    {
      "Number": 409,
      "Name": "Rampardos",
      "Card": "images\\PokemonCards-133.png",
      "Quantity": 1,
      "Set": "Mysterious Treasures",
      "Code": "dp2-33",
      "Language": "EN",
      "Special": null
    },
    {
      "Number": 412,
      "Name": "Burmy",
      "Card": "images\\PokemonCards-93.png",
      "Quantity": 1,
      "Set": "Secret Wonders",
      "Code": "dp3-78",
      "Language": "EN",
      "Special": {
        "Form": "Plant Cloak"
      }
    },
    {
      "Number": 415,
      "Name": "Combee",
      "Card": "images\\PokemonCards-11.png",
      "Quantity": 1,
      "Set": "Majestic Dawn",
      "Code": "md-59",
      "Language": "EN",
      "Special": null
    },
    {
      "Number": 419,
      "Name": "Floatzel",
      "Card": "images\\PokemonCards-125.png",
      "Quantity": 1,
      "Set": "Diamond & Pearl",
      "Code": "dp1-26",
      "Language": "EN",
      "Special": null
    },
    {
      "Number": 427,
      "Name": "Buneary",
      "Card": "images\\PokemonCards-135.png",
      "Quantity": 1,
      "Set": "Majestic Dawn",
      "Code": "dp5-53",
      "Language": "EN",
      "Special": null
    },
    {
      "Number": 429,
      "Name": "Mismagius",
      "Card": "images\\PokemonCards-44.png",
      "Quantity": 1,
      "Set": "Diamond & Pearl",
      "Code": "dp1-10",
      "Language": "EN",
      "Special": null
    },
    {
      "Number": 430,
      "Name": "Honchkrow",
      "Card": "images\\PokemonCards-14.png",
      "Quantity": 1,
      "Set": "Secret Wonders",
      "Code": "dp3-132",
      "Language": "EN",
      "Special": {
        "LV. X": true
      }
    },
    {
      "Number": 432,
      "Name": "Purugly",
      "Card": "images\\PokemonCards-131.png",
      "Quantity": 1,
      "Set": "Diamond & Pearl",
      "Code": "dp1-36",
      "Language": "EN",
      "Special": null
    },
    {
      "Number": 448,
      "Name": "Lucario",
      "Card": "images\\PokemonCards-82.png",
      "Quantity": 1,
      "Set": "DP Black Star Promos",
      "Code": "dpp-dp12",
      "Language": "EN",
      "Special": {
        "LV. X": true
      }
    },
    {
      "Number": 450,
      "Name": "Hippowdon",
      "Card": "images\\PokemonCards-142.png",
      "Quantity": 1,
      "Set": "Diamond & Pearl",
      "Code": "dp1-29",
      "Language": "EN",
      "Special": null
    },
    {
      "Number": 464,
      "Name": "Rhyperior",
      "Card": "images\\PokemonCards-53.png",
      "Quantity": 1,
      "Set": "Diamond & Pearl",
      "Code": "dp1-12",
      "Language": "EN",
      "Special": null
    },
    {
      "Number": 466,
      "Name": "Electivire",
      "Card": "images\\PokemonCards-55.png",
      "Quantity": 1,
      "Set": "Diamond & Pearl",
      "Code": "dp1-3",
      "Language": "EN",
      "Special": null
    },
    {
      "Number": 467,
      "Name": "Magmortar",
      "Card": "images\\PokemonCards-1.png",
      "Quantity": 1,
      "Set": "Paldean Fates",
      "Code": "sv4pt5-10",
      "Language": "EN",
      "Special": null
    },
    {
      "Number": 474,
      "Name": "Porygon-Z",
      "Card": "images\\PokemonCards-51.png",
      "Quantity": 1,
      "Set": "Great Encounters",
      "Code": "dp4-6",
      "Language": "EN",
      "Special": null
    },
    {
      "Number": 484,
      "Name": "Palkia",
      "Card": "images\\PokemonCards-67.png",
      "Quantity": 1,
      "Set": "Great Encounters",
      "Code": "dp4-26",
      "Language": "EN",
      "Special": null
    },
    {
      "Number": 489,
      "Name": "Phione",
      "Card": "images\\PokemonCards-173.png",
      "Quantity": 1,
      "Set": "Transformation Mask JP",
      "Code": "sv6-175",
      "Language": "JP",
      "Special": null
    },
    {
      "Number": 556,
      "Name": "Maractus",
      "Card": "images\\PokemonCards-4.png",
      "Quantity": 1,
      "Set": "Paldean Fates",
      "Code": "sv4pt5-3",
      "Language": "EN",
      "Special": null
    },
    {
      "Number": 571,
      "Name": "Zoroark",
      "Card": "images\\PokemonCards-179.png",
      "Quantity": 1,
      "Set": "Lost Origin",
      "Code": "swsh11-76",
      "Language": "EN",
      "Special": {
        "Form": "Hisuian"
      }
    },
    {
      "Number": 646,
      "Name": "Kyurem",
      "Card": "images\\PokemonCards-176.png",
      "Quantity": 1,
      "Set": "Fates Collide",
      "Code": "xy10-21",
      "Language": "EN",
      "Special": {
        "Form": "White"
      }
    },
    {
      "Number": 716,
      "Name": "Xerneas",
      "Card": "images\\PokemonCards-177.png",
      "Quantity": 1,
      "Set": "BREAKthrough",
      "Code": "xy8-107",
      "Language": "EN",
      "Special": null
    },
    {
      "Number": 1025,
      "Name": "Pecharunt",
      "Card": "images\\PokemonCards-188.png",
      "Quantity": 1,
      "Set": "Shrouded Fable",
      "Code": "sv6pt5-39",
      "Language": "EN",
      "Special": {
        "ex": true
      }
    },
    {
      "Number": 570,
      "Name": "Zorua",
      "Card": "images\\PokemonCards-189.png",
      "Quantity": 1,
      "Set": "Shrouded Fable",
      "Code": "sv6pt5-31",
      "Language": "EN",
      "Special": null
    },
    {
      "Number": 229,
      "Name": "Houndoom",
      "Card": "images\\PokemonCards-190.png",
      "Quantity": 1,
      "Set": "Shrouded Fable",
      "Code": "sv6pt5-8",
      "Language": "EN",
      "Special": null
    },
    {
      "Number": 649,
      "Name": "Genesect",
      "Card": "images\\PokemonCards-191.png",
      "Quantity": 1,
      "Set": "Shrouded Fable",
      "Code": "sv6pt5-40",
      "Language": "EN",
      "Special": null
    },
    {
      "Number": 687,
      "Name": "Malamar",
      "Card": "images\\PokemonCards-192.png",
      "Quantity": 1,
      "Set": "Shrouded Fable",
      "Code": "sv6pt5-34",
      "Language": "EN",
      "Special": null
    },
    {
      "Number": 596,
      "Name": "Galvantula",
      "Card": "images\\PokemonCards-193.png",
      "Quantity": 1,
      "Set": "Shrouded Fable",
      "Code": "sv6pt5-2",
      "Language": "EN",
      "Special": null
    },
    {
      "Number": 116,
      "Name": "Horsea",
      "Card": "images\\PokemonCards-194.png",
      "Quantity": 3,
      "Set": "Shrouded Fable",
      "Code": "sv6pt5-10",
      "Language": "EN",
      "Special": null
    },
    {
      "Number": 52,
      "Name": "Meowth",
      "Card": "images\\PokemonCards-195.png",
      "Quantity": 1,
      "Set": "Shrouded Fable",
      "Code": "sv6pt5-48",
      "Language": "EN",
      "Special": null
    },
    {
      "Number": 454,
      "Name": "Toxicroak",
      "Card": "images\\PokemonCards-196.png",
      "Quantity": 2,
      "Set": "Shrouded Fable",
      "Code": "sv6pt5-24",
      "Language": "EN",
      "Special": null
    },
    {
      "Number": 676,
      "Name": "Furfrou",
      "Card": "images\\PokemonCards-197.png",
      "Quantity": 1,
      "Set": "Shrouded Fable",
      "Code": "sv6pt5-51",
      "Language": "EN",
      "Special": null
    },
    {
      "Number": 994,
      "Name": "Iron Moth",
      "Card": "images\\PokemonCards-198.png",
      "Quantity": 1,
      "Set": "Shrouded Fable",
      "Code": "sv6pt5-9",
      "Language": "EN",
      "Special": {
        "paradox": "Future"
      }
    },
    {
      "Number": 169,
      "Name": "Crobat",
      "Card": "images\\PokemonCards-199.png",
      "Quantity": 1,
      "Set": "Shrouded Fable",
      "Code": "sv6pt5-29",
      "Language": "EN",
      "Special": null
    },
    {
      "Number": 901,
      "Name": "Ursaluna",
      "Card": "images\\PokemonCards-200.png",
      "Quantity": 2,
      "Set": "Shrouded Fable",
      "Code": "sv6pt5-25",
      "Language": "EN",
      "Special": {
        "Form": "Bloodmoon"
      }
    },
    {
      "Number": 724,
      "Name": "Decidueye",
      "Card": "images\\PokemonCards-201.png",
      "Quantity": 1,
      "Set": "Shrouded Fable",
      "Code": "sv6pt5-5",
      "Language": "EN",
      "Special": null
    },
    {
      "Number": 97,
      "Name": "Hypno",
      "Card": "images\\PokemonCards-202.png",
      "Quantity": 2,
      "Set": "Shrouded Fable",
      "Code": "sv6pt5-17",
      "Language": "EN",
      "Special": null
    },
    {
      "Number": 760,
      "Name": "Bewear",
      "Card": "images\\PokemonCards-203.png",
      "Quantity": 1,
      "Set": "Shrouded Fable",
      "Code": "sv6pt5-53",
      "Language": "EN",
      "Special": null
    },
    {
      "Number": 355,
      "Name": "Duskull",
      "Card": "images\\PokemonCards-204.png",
      "Quantity": 1,
      "Set": "Shrouded Fable",
      "Code": "sv6pt5-18",
      "Language": "EN",
      "Special": null
    },
    {
      "Number": 965,
      "Name": "Varoom",
      "Card": "images\\PokemonCards-205.png",
      "Quantity": 1,
      "Set": "Shrouded Fable",
      "Code": "sv6pt5-43",
      "Language": "EN",
      "Special": null
    },
    {
      "Number": 787,
      "Name": "Tapu Bulu",
      "Card": "images\\PokemonCards-206.png",
      "Quantity": 1,
      "Set": "Shrouded Fable",
      "Code": "sv6pt5-6",
      "Language": "EN",
      "Special": null
    },
    {
      "Number": 646,
      "Name": "Kyurem",
      "Card": "images\\PokemonCards-207.png",
      "Quantity": 1,
      "Set": "Shrouded Fable",
      "Code": "sv6pt5-47",
      "Language": "EN",
      "Special": null
    },
    {
      "Number": 717,
      "Name": "Yveltal",
      "Card": "images\\PokemonCards-208.png",
      "Quantity": 1,
      "Set": "Shrouded Fable",
      "Code": "sv6pt5-35",
      "Language": "EN",
      "Special": null
    },
    {
      "Number": 215,
      "Name": "Sneasel",
      "Card": "images\\PokemonCards-209.png",
      "Quantity": 1,
      "Set": "Shrouded Fable",
      "Code": "sv6pt5-13",
      "Language": "EN",
      "Special": null
    },
    {
      "Number": 610,
      "Name": "Axew",
      "Card": "images\\PokemonCards-210.png",
      "Quantity": 1,
      "Set": "Shrouded Fable",
      "Code": "sv6pt5-44",
      "Language": "EN",
      "Special": null
    },
    {
      "Number": 42,
      "Name": "Golbat",
      "Card": "images\\PokemonCards-211.png",
      "Quantity": 1,
      "Set": "Shrouded Fable",
      "Code": "sv6pt5-28",
      "Language": "EN",
      "Special": null
    },
    {
      "Number": 41,
      "Name": "Zubat",
      "Card": "images\\PokemonCards-212.png",
      "Quantity": 2,
      "Set": "Shrouded Fable",
      "Code": "sv6pt5-27",
      "Language": "EN",
      "Special": null
    },
    {
      "Number": 96,
      "Name": "Drowzee",
      "Card": "images\\PokemonCards-213.png",
      "Quantity": 1,
      "Set": "Shrouded Fable",
      "Code": "sv6pt5-16",
      "Language": "EN",
      "Special": null
    },
    {
      "Number": 722,
      "Name": "Rowlet",
      "Card": "images\\PokemonCards-214.png",
      "Quantity": 1,
      "Set": "Shrouded Fable",
      "Code": "sv6pt5-3",
      "Language": "EN",
      "Special": null
    },
    {
      "Number": 878,
      "Name": "Cufant",
      "Card": "images\\PokemonCards-215.png",
      "Quantity": 1,
      "Set": "Shrouded Fable",
      "Code": "sv6pt5-41",
      "Language": "EN",
      "Special": null
    },
    {
      "Number": 717,
      "Name": "Yveltal",
      "Card": "images\\PokemonCards-185.png",
      "Quantity": 1,
      "Set": "XY",
      "Code": "xy1-79",
      "Language": "EN",
      "Special": {
        "EX": true
      }
    }
  ],
  "other": [
    {
      "Type": "Energy",
      "Name": "Basic Lightning Energy",
      "Card": "images\\PokemonCards-154.png",
      "Quantity": 2,
      "Set": "Paldean Fates",
      "Code": "sve-4"
    },
    {
      "Type": "Energy",
      "Name": "Psychic Energy",
      "Card": "images\\PokemonCards-156.png",
      "Quantity": 13,
      "Set": "Base Set 2",
      "Code": "base4-129"
    },
    {
      "Type": "Energy",
      "Name": "Water Energy",
      "Card": "images\\PokemonCards-158.png",
      "Quantity": 15,
      "Set": "Base Set 2",
      "Code": "base4-130"
    },
    {
      "Type": "Item",
      "Name": "Defender",
      "Card": "images\\PokemonCards-167.png",
      "Quantity": 1,
      "Set": "Base Set 2",
      "Code": "base4-109"
    },
    {
      "Type": "Item",
      "Name": "Electric Generator",
      "Card": "images\\PokemonCards-155.png",
      "Quantity": 1,
      "Set": "Paldean Fates",
      "Code": "sv4pt5-79"
    },
    {
      "Type": "Item",
      "Name": "Great Ball",
      "Card": "images\\PokemonCards-170.png",
      "Quantity": 1,
      "Set": "Power Keepers",
      "Code": "ex16-77"
    },
    {
      "Type": "Item",
      "Name": "Holon Fossil",
      "Card": "images\\PokemonCards-162.png",
      "Quantity": 1,
      "Set": "Holon Phantoms",
      "Code": "ex13-86"
    },
    {
      "Type": "Item",
      "Name": "Master Ball",
      "Card": "images\\PokemonCards-161.png",
      "Quantity": 1,
      "Set": "Power Keepers",
      "Code": "ex16-78"
    },
    {
      "Type": "Item",
      "Name": "Mysterious Fossil",
      "Card": "images\\PokemonCards-168.png",
      "Quantity": 1,
      "Set": "Holon Phantoms",
      "Code": "ex13-92"
    },
    {
      "Type": "Item",
      "Name": "Poke Ball",
      "Card": "images\\PokemonCards-169.png",
      "Quantity": 1,
      "Set": "Unseen Forces",
      "Code": "ex10-87"
    },
    {
      "Type": "Item",
      "Name": "Potion",
      "Card": "images\\PokemonCards-164.png",
      "Quantity": 1,
      "Set": "Base Set 2",
      "Code": "base4-122"
    },
    {
      "Type": "Item",
      "Name": "Super Potion",
      "Card": "images\\PokemonCards-166.png",
      "Quantity": 1,
      "Set": "Base Set 2",
      "Code": "base4-117"
    },
    {
      "Type": "Stadium",
      "Name": "Batle Frontier",
      "Card": "images\\PokemonCards-157.png",
      "Quantity": 2,
      "Set": "Power Keepers",
      "Code": "ex16-71"
    },
    {
      "Type": "Stadium",
      "Name": "Lake Boundary",
      "Card": "images\\PokemonCards-160.png",
      "Quantity": 1,
      "Set": "Mysterious Treasures",
      "Code": "dp2-112"
    },
    {
      "Type": "Supporter",
      "Name": "Paldean Student",
      "Card": "images\\PokemonCards-153.png",
      "Quantity": 1,
      "Set": "Paldean Fates",
      "Code": "sv4pt5-85"
    },
    {
      "Type": "Trainer",
      "Name": "Computer Search",
      "Card": "images\\PokemonCards-165.png",
      "Quantity": 1,
      "Set": "Base Set 2",
      "Code": "base4-101"
    },
    {
      "Type": "Trainer",
      "Name": "Gust of Wind",
      "Card": "images\\PokemonCards-163.png",
      "Quantity": 3,
      "Set": "Base Set 2",
      "Code": "base4-120"
    },
    {
      "Type": "Item",
      "Name": "Night Stretcher",
      "Card": "images\\PokemonCards-216.png",
      "Quantity": 1,
      "Set": "Shrouded Fable",
      "Code": "sv6pt5-61"
    },
    {
      "Type": "Supporter",
      "Name": "Colress's Tenacity",
      "Card": "images\\PokemonCards-217.png",
      "Quantity": 1,
      "Set": "Shrouded Fable",
      "Code": "sv6pt5-57"
    },
    {
      "Type": "Supporter",
      "Name": "Janine's Secret Art",
      "Card": "images\\PokemonCards-218.png",
      "Quantity": 1,
      "Set": "Shrouded Fable",
      "Code": "sv6pt5-88"
    },
    {
      "Type": "Energy",
      "Name": "Basic Water Energy",
      "Card": "images\\PokemonCards-219.png",
      "Quantity": 1,
      "Set": "Shrouded Fable",
      "Code": "sve-3"
    },
    {
      "Type": "Stadium",
      "Name": "Academy at Night",
      "Card": "images\\PokemonCards-220.png",
      "Quantity": 1,
      "Set": "Shrouded Fable",
      "Code": "sv6pt5-54"
    },
    {
      "Type": "Tool",
      "Name": "Binding Mochi",
      "Card": "images\\PokemonCards-221.png",
      "Quantity": 1,
      "Set": "Shrouded Fable",
      "Code": "sv6pt5-55"
    },
    {
      "Type": "Energy",
      "Name": "Basic Dark Energy",
      "Card": "images\\PokemonCards-222.png",
      "Quantity": 1,
      "Set": "Shrouded Fable",
      "Code": "sve-7"
    },
    {
      "Type": "Supporter",
      "Name": "Janine's Secret Art",
      "Card": "images\\PokemonCards-223.png",
      "Quantity": 1,
      "Set": "Shrouded Fable",
      "Code": "sv6pt5-59"
    },
    {
      "Type": "Energy",
      "Name": "Basic Metal Energy",
      "Card": "images\\PokemonCards-224.png",
      "Quantity": 1,
      "Set": "Shrouded Fable",
      "Code": "sve-8"
    },
    {
      "Type": "Trainer",
      "Name": "Switch",
      "Card": "images\\PokemonCards-159.png",
      "Quantity": 2,
      "Set": "Base Set 2",
      "Code": "base4-123"
    }
  ]
}